{
  "version": "v20260604_0006",
  "metrics": {
    "10min": {
      "mae_cv": 91.31,
      "mae_std": 5.04,
      "mae_train": 67.61,
      "rmse": 122.74,
      "r2": 0.6437
    },
    "1h": {
      "mae_cv": 100.27,
      "mae_std": 4.89,
      "mae_train": 73.67,
      "rmse": 126.89,
      "r2": 0.6192
    },
    "6h": {
      "mae_cv": 104.14,
      "mae_std": 9.78,
      "mae_train": 74.76,
      "rmse": 127.88,
      "r2": 0.613
    },
    "24h": {
      "mae_cv": 103.39,
      "mae_std": 8.54,
      "mae_train": 77.5,
      "rmse": 130.0,
      "r2": 0.6017
    }
  }
}